MANIFEST.in
README.md
setup.py
ddshape/__init__.py
ddshape/break_shell.py
ddshape/inc.py
ddshape/intersect_shell.py
ddshape/sphere.py
ddshape.egg-info/PKG-INFO
ddshape.egg-info/SOURCES.txt
ddshape.egg-info/dependency_links.txt
ddshape.egg-info/top_level.txt
ddshape/Template/ddscat.tpl
ddshape/Template/fielda.tpl
ddshape/Template/shape.tpl