Metadata-Version: 1.0
Name: ddshape
Version: 0.38
Summary: this is a package which include some modules that you can use them to create shape.dat used by ddscat
Home-page: https://github.com/xingtingyang/ddshape
Author: Xing
Author-email: 1281961491@qq.com
License: BSD style
Platform: UNKNOWN
